modelrunner_ai/__init__.py
modelrunner_ai/auth.py
modelrunner_ai/client.py
modelrunner_ai/py.typed
modelrunner_ai-0.1.0.dist-info/METADATA
modelrunner_ai-0.1.0.dist-info/WHEEL
modelrunner_ai-0.1.0.dist-info/top_level.txt
modelrunner_ai-0.1.0.dist-info/RECORD
