Metadata-Version: 2.4
Name: modelrunner-ai
Version: 0.1.0
Summary: Python client for modelrunner.ai
Author: Features & Labels <support@modelrunner.ai>
Project-URL: homepage, https://modelrunner.ai
Project-URL: repository, https://github.com/modelrunner/modelrunner
Requires-Python: >=3.8
Requires-Dist: httpx<1,>=0.21.0
Requires-Dist: httpx-sse<0.5,>=0.4.0
Provides-Extra: docs
Requires-Dist: sphinx; extra == "docs"
Requires-Dist: sphinx-rtd-theme; extra == "docs"
Requires-Dist: sphinx-autodoc-typehints; extra == "docs"
Provides-Extra: test
Requires-Dist: pytest; extra == "test"
Requires-Dist: pytest-asyncio; extra == "test"
Requires-Dist: pytest-mock; extra == "test"
Requires-Dist: pillow; extra == "test"
Provides-Extra: dev
Requires-Dist: modelrunner_ai[docs,test]; extra == "dev"
